[
    {
        "cook_attempts": 0,
        "interaction_id": "interaction1",
        "views": 150,
        "rating": 3.4,
        "user_id": "user1",
        "timestamp": "2025-11-20T10:05:13Z",
        "recipe_id": "recipe1_paneer_curry_with_chapati",
        "likes": 1,
        "id": "interaction1"
    },
    {
        "cook_attempts": 1,
        "interaction_id": "interaction10",
        "views": 166,
        "rating": 4.7,
        "user_id": "user10",
        "timestamp": "2025-11-20T10:05:13Z",
        "recipe_id": "recipe5_chicken_curry",
        "likes": 0,
        "id": "interaction10"
    },
    {
        "cook_attempts": 1,
        "interaction_id": "interaction11",
        "views": 106,
        "rating": 4.9,
        "user_id": "user11",
        "timestamp": "2025-11-20T10:05:13Z",
        "recipe_id": "recipe6_egg_bhurji",
        "likes": 1,
        "id": "interaction11"
    },
    {
        "cook_attempts": 3,
        "interaction_id": "interaction12",
        "views": 72,
        "rating": 3.5,
        "user_id": "user12",
        "timestamp": "2025-11-20T10:05:13Z",
        "recipe_id": "recipe6_egg_bhurji",
        "likes": 0,
        "id": "interaction12"
    },
    {
        "cook_attempts": 4,
        "interaction_id": "interaction13",
        "views": 79,
        "rating": 3.7,
        "user_id": "user13",
        "timestamp": "2025-11-20T10:05:13Z",
        "recipe_id": "recipe7_dal_tadka",
        "likes": 0,
        "id": "interaction13"
    },
    {
        "cook_attempts": 0,
        "interaction_id": "interaction14",
        "views": 200,
        "rating": 4.2,
        "user_id": "user14",
        "timestamp": "2025-11-20T10:05:13Z",
        "recipe_id": "recipe7_dal_tadka",
        "likes": 0,
        "id": "interaction14"
    },
    {
        "cook_attempts": 3,
        "interaction_id": "interaction15",
        "views": 200,
        "rating": 3.2,
        "user_id": "user15",
        "timestamp": "2025-11-20T10:05:13Z",
        "recipe_id": "recipe8_chole_bhature",
        "likes": 1,
        "id": "interaction15"
    },
    {
        "cook_attempts": 1,
        "interaction_id": "interaction16",
        "views": 173,
        "rating": 4.6,
        "user_id": "user16",
        "timestamp": "2025-11-20T10:05:13Z",
        "recipe_id": "recipe8_chole_bhature",
        "likes": 0,
        "id": "interaction16"
    },
    {
        "cook_attempts": 4,
        "interaction_id": "interaction17",
        "views": 148,
        "rating": 4.1,
        "user_id": "user17",
        "timestamp": "2025-11-20T10:05:13Z",
        "recipe_id": "recipe9_pasta_alfredo",
        "likes": 0,
        "id": "interaction17"
    },
    {
        "cook_attempts": 0,
        "interaction_id": "interaction18",
        "views": 2,
        "rating": 4.5,
        "user_id": "user18",
        "timestamp": "2025-11-20T10:05:13Z",
        "recipe_id": "recipe9_pasta_alfredo",
        "likes": 1,
        "id": "interaction18"
    },
    {
        "cook_attempts": 2,
        "interaction_id": "interaction19",
        "views": 196,
        "rating": 4.9,
        "user_id": "user19",
        "timestamp": "2025-11-20T10:05:13Z",
        "recipe_id": "recipe10_veg_biryani",
        "likes": 0,
        "id": "interaction19"
    },
    {
        "cook_attempts": 0,
        "interaction_id": "interaction2",
        "views": 93,
        "rating": 3.1,
        "user_id": "user2",
        "timestamp": "2025-11-20T10:05:13Z",
        "recipe_id": "recipe1_paneer_curry_with_chapati",
        "likes": 1,
        "id": "interaction2"
    },
    {
        "cook_attempts": 1,
        "interaction_id": "interaction20",
        "views": 179,
        "rating": 4.5,
        "user_id": "user20",
        "timestamp": "2025-11-20T10:05:13Z",
        "recipe_id": "recipe10_veg_biryani",
        "likes": 0,
        "id": "interaction20"
    },
    {
        "cook_attempts": 4,
        "interaction_id": "interaction21",
        "views": 67,
        "rating": 4.5,
        "user_id": "user21",
        "timestamp": "2025-11-20T10:05:13Z",
        "recipe_id": "recipe11_sambar_rice",
        "likes": 1,
        "id": "interaction21"
    },
    {
        "cook_attempts": 3,
        "interaction_id": "interaction22",
        "views": 4,
        "rating": 3.0,
        "user_id": "user22",
        "timestamp": "2025-11-20T10:05:13Z",
        "recipe_id": "recipe11_sambar_rice",
        "likes": 0,
        "id": "interaction22"
    },
    {
        "cook_attempts": 2,
        "interaction_id": "interaction23",
        "views": 86,
        "rating": 3.1,
        "user_id": "user23",
        "timestamp": "2025-11-20T10:05:13Z",
        "recipe_id": "recipe12_poha",
        "likes": 0,
        "id": "interaction23"
    },
    {
        "cook_attempts": 0,
        "interaction_id": "interaction24",
        "views": 61,
        "rating": 3.8,
        "user_id": "user24",
        "timestamp": "2025-11-20T10:05:13Z",
        "recipe_id": "recipe12_poha",
        "likes": 1,
        "id": "interaction24"
    },
    {
        "cook_attempts": 1,
        "interaction_id": "interaction25",
        "views": 81,
        "rating": 4.0,
        "user_id": "user25",
        "timestamp": "2025-11-20T10:05:13Z",
        "recipe_id": "recipe13_upma",
        "likes": 0,
        "id": "interaction25"
    },
    {
        "cook_attempts": 1,
        "interaction_id": "interaction26",
        "views": 10,
        "rating": 5.0,
        "user_id": "user26",
        "timestamp": "2025-11-20T10:05:13Z",
        "recipe_id": "recipe13_upma",
        "likes": 0,
        "id": "interaction26"
    },
    {
        "cook_attempts": 2,
        "interaction_id": "interaction27",
        "views": 27,
        "rating": 3.4,
        "user_id": "user27",
        "timestamp": "2025-11-20T10:05:14Z",
        "recipe_id": "recipe14_roti_sabzi",
        "likes": 0,
        "id": "interaction27"
    },
    {
        "cook_attempts": 0,
        "interaction_id": "interaction28",
        "views": 161,
        "rating": 4.6,
        "user_id": "user28",
        "timestamp": "2025-11-20T10:05:14Z",
        "recipe_id": "recipe14_roti_sabzi",
        "likes": 1,
        "id": "interaction28"
    },
    {
        "cook_attempts": 1,
        "interaction_id": "interaction29",
        "views": 90,
        "rating": 3.6,
        "user_id": "user29",
        "timestamp": "2025-11-20T10:05:14Z",
        "recipe_id": "recipe15_paneer_butter_masala",
        "likes": 1,
        "id": "interaction29"
    },
    {
        "cook_attempts": 2,
        "interaction_id": "interaction3",
        "views": 171,
        "rating": 4.7,
        "user_id": "user3",
        "timestamp": "2025-11-20T10:05:13Z",
        "recipe_id": "recipe2_veg_fried_rice",
        "likes": 1,
        "id": "interaction3"
    },
    {
        "cook_attempts": 0,
        "interaction_id": "interaction30",
        "views": 28,
        "rating": 3.7,
        "user_id": "user30",
        "timestamp": "2025-11-20T10:05:14Z",
        "recipe_id": "recipe15_paneer_butter_masala",
        "likes": 1,
        "id": "interaction30"
    },
    {
        "cook_attempts": 3,
        "interaction_id": "interaction31",
        "views": 141,
        "rating": 4.9,
        "user_id": "user1",
        "timestamp": "2025-11-20T10:05:14Z",
        "recipe_id": "recipe16_mixed_veg_curry",
        "likes": 1,
        "id": "interaction31"
    },
    {
        "cook_attempts": 2,
        "interaction_id": "interaction32",
        "views": 172,
        "rating": 4.5,
        "user_id": "user2",
        "timestamp": "2025-11-20T10:05:14Z",
        "recipe_id": "recipe16_mixed_veg_curry",
        "likes": 0,
        "id": "interaction32"
    },
    {
        "cook_attempts": 3,
        "interaction_id": "interaction33",
        "views": 120,
        "rating": 4.1,
        "user_id": "user3",
        "timestamp": "2025-11-20T10:05:14Z",
        "recipe_id": "recipe17_tomato_soup",
        "likes": 0,
        "id": "interaction33"
    },
    {
        "cook_attempts": 1,
        "interaction_id": "interaction34",
        "views": 39,
        "rating": 4.4,
        "user_id": "user4",
        "timestamp": "2025-11-20T10:05:14Z",
        "recipe_id": "recipe17_tomato_soup",
        "likes": 0,
        "id": "interaction34"
    },
    {
        "cook_attempts": 2,
        "interaction_id": "interaction35",
        "views": 2,
        "rating": 4.3,
        "user_id": "user5",
        "timestamp": "2025-11-20T10:05:14Z",
        "recipe_id": "recipe18_veg_sandwich",
        "likes": 0,
        "id": "interaction35"
    },
    {
        "cook_attempts": 1,
        "interaction_id": "interaction36",
        "views": 128,
        "rating": 3.8,
        "user_id": "user6",
        "timestamp": "2025-11-20T10:05:14Z",
        "recipe_id": "recipe18_veg_sandwich",
        "likes": 1,
        "id": "interaction36"
    },
    {
        "cook_attempts": 4,
        "interaction_id": "interaction37",
        "views": 16,
        "rating": 3.8,
        "user_id": "user7",
        "timestamp": "2025-11-20T10:05:14Z",
        "recipe_id": "recipe19_fruit_salad",
        "likes": 0,
        "id": "interaction37"
    },
    {
        "cook_attempts": 4,
        "interaction_id": "interaction38",
        "views": 100,
        "rating": 4.5,
        "user_id": "user8",
        "timestamp": "2025-11-20T10:05:14Z",
        "recipe_id": "recipe19_fruit_salad",
        "likes": 0,
        "id": "interaction38"
    },
    {
        "cook_attempts": 0,
        "interaction_id": "interaction39",
        "views": 184,
        "rating": 4.6,
        "user_id": "user9",
        "timestamp": "2025-11-20T10:05:14Z",
        "recipe_id": "recipe20_jeera_rice",
        "likes": 1,
        "id": "interaction39"
    },
    {
        "cook_attempts": 1,
        "interaction_id": "interaction4",
        "views": 160,
        "rating": 4.1,
        "user_id": "user4",
        "timestamp": "2025-11-20T10:05:13Z",
        "recipe_id": "recipe2_veg_fried_rice",
        "likes": 1,
        "id": "interaction4"
    },
    {
        "cook_attempts": 4,
        "interaction_id": "interaction40",
        "views": 74,
        "rating": 3.3,
        "user_id": "user10",
        "timestamp": "2025-11-20T10:05:14Z",
        "recipe_id": "recipe20_jeera_rice",
        "likes": 0,
        "id": "interaction40"
    },
    {
        "cook_attempts": 4,
        "interaction_id": "interaction41",
        "views": 75,
        "rating": 3.1,
        "user_id": "user11",
        "timestamp": "2025-11-20T10:05:14Z",
        "recipe_id": "recipe21_curd_rice",
        "likes": 0,
        "id": "interaction41"
    },
    {
        "cook_attempts": 0,
        "interaction_id": "interaction42",
        "views": 81,
        "rating": 4.8,
        "user_id": "user12",
        "timestamp": "2025-11-20T10:05:14Z",
        "recipe_id": "recipe21_curd_rice",
        "likes": 0,
        "id": "interaction42"
    },
    {
        "cook_attempts": 4,
        "interaction_id": "interaction5",
        "views": 36,
        "rating": 3.5,
        "user_id": "user5",
        "timestamp": "2025-11-20T10:05:13Z",
        "recipe_id": "recipe3_masala_dosa",
        "likes": 0,
        "id": "interaction5"
    },
    {
        "cook_attempts": 0,
        "interaction_id": "interaction6",
        "views": 72,
        "rating": 3.8,
        "user_id": "user6",
        "timestamp": "2025-11-20T10:05:13Z",
        "recipe_id": "recipe3_masala_dosa",
        "likes": 0,
        "id": "interaction6"
    },
    {
        "cook_attempts": 0,
        "interaction_id": "interaction7",
        "views": 137,
        "rating": 3.7,
        "user_id": "user7",
        "timestamp": "2025-11-20T10:05:13Z",
        "recipe_id": "recipe4_aloo_paratha",
        "likes": 0,
        "id": "interaction7"
    },
    {
        "cook_attempts": 4,
        "interaction_id": "interaction8",
        "views": 118,
        "rating": 4.7,
        "user_id": "user8",
        "timestamp": "2025-11-20T10:05:13Z",
        "recipe_id": "recipe4_aloo_paratha",
        "likes": 0,
        "id": "interaction8"
    },
    {
        "cook_attempts": 2,
        "interaction_id": "interaction9",
        "views": 86,
        "rating": 3.2,
        "user_id": "user9",
        "timestamp": "2025-11-20T10:05:13Z",
        "recipe_id": "recipe5_chicken_curry",
        "likes": 1,
        "id": "interaction9"
    }
]